pelican_plugin_installer/__init__.py
pelican_plugin_installer/cli.py
pelican_plugin_installer/commands.py
pelican_plugin_installer/exceptions.py
pelican_plugin_installer/manager.py
pelican_plugin_installer-0.1.0.dist-info/DESCRIPTION.rst
pelican_plugin_installer-0.1.0.dist-info/METADATA
pelican_plugin_installer-0.1.0.dist-info/RECORD
pelican_plugin_installer-0.1.0.dist-info/WHEEL
pelican_plugin_installer-0.1.0.dist-info/entry_points.txt
pelican_plugin_installer-0.1.0.dist-info/metadata.json
pelican_plugin_installer-0.1.0.dist-info/top_level.txt
