Metadata-Version: 2.0
Name: pelican-plugin-installer
Version: 0.1.0
Summary: Installs Pelican Plugins in an easy way
Home-page: https://github.com/kplaube/pelican-plugin-installer
Author: Klaus Laube
Author-email: kplaube@gmail.com
License: GPL3
Platform: any
Classifier: Development Status :: 4 - Beta
Classifier: Environment :: Console
Classifier: Intended Audience :: Developers
Classifier: License :: OSI Approved :: GNU General Public License v3 (GPLv3)
Classifier: Operating System :: POSIX
Classifier: Operating System :: MacOS
Classifier: Operating System :: Unix
Classifier: Programming Language :: Python
Classifier: Programming Language :: Python :: 2
Classifier: Programming Language :: Python :: 3
Classifier: Topic :: Software Development :: Libraries :: Python Modules
Requires-Dist: click
